toynn/__init__.py
toynn/factory.py
toynn/model.py
toynn-0.1.0.dist-info/LICENSE.txt
toynn-0.1.0.dist-info/METADATA
toynn-0.1.0.dist-info/WHEEL
toynn-0.1.0.dist-info/top_level.txt
toynn-0.1.0.dist-info/RECORD
